dtools/fp/__init__.py
dtools/fp/bool.py
dtools/fp/function.py
dtools/fp/lazy.py
dtools/fp/py.typed
dtools/fp/singletons.py
dtools/fp/state.py
dtools_fp-2.0.0.dist-info/licenses/LICENSE
dtools_fp-2.0.0.dist-info/WHEEL
dtools_fp-2.0.0.dist-info/METADATA
dtools_fp-2.0.0.dist-info/RECORD
